__init__.py
anime_gen.py
anime_gen-1.0.0.dist-info/LICENSE
anime_gen-1.0.0.dist-info/METADATA
anime_gen-1.0.0.dist-info/WHEEL
anime_gen-1.0.0.dist-info/top_level.txt
anime_gen-1.0.0.dist-info/RECORD
