Metadata-Version: 2.1
Name: anime-gen
Version: 1.0.0
Summary: anime/manga image/wallpaper generator
Author: Nowkzy
License: LICENSE
License-File: LICENSE
